omegapoint/__init__.py
omegapoint/omegapoint.py
omegapoint/schema.py
omegapoint/utils.py
omegapoint-0.0.3.dist-info/LICENSE
omegapoint-0.0.3.dist-info/METADATA
omegapoint-0.0.3.dist-info/WHEEL
omegapoint-0.0.3.dist-info/top_level.txt
omegapoint-0.0.3.dist-info/RECORD
