Metadata-Version: 2.1
Name: omegapoint
Version: 0.0.3
Summary: Omega Point API Python Library
Home-page: https://github.com/RossFabricant/omegapoint
Author: Ross Fabricant
License: UNKNOWN
Platform: UNKNOWN
Classifier: Programming Language :: Python :: 3
Classifier: License :: OSI Approved :: MIT License
Classifier: Operating System :: OS Independent
Requires-Python: >=3.6
Requires-Dist: numpy
Requires-Dist: pandas
Requires-Dist: requests
Requires-Dist: sgqlc
